recaptcha_challenger/__init__.py
recaptcha_challenger/_demo.py
recaptcha_challenger/core.py
recaptcha_challenger/exceptions.py
recaptcha_challenger/settings.py
recaptcha_challenger/utils.py
recaptcha_challenger/solutions/__init__.py
recaptcha_challenger/solutions/kernel.py
recaptcha_challenger/solutions/yolo.py
recaptcha_challenger-0.0.1.dist-info/LICENSE
recaptcha_challenger-0.0.1.dist-info/METADATA
recaptcha_challenger-0.0.1.dist-info/WHEEL
recaptcha_challenger-0.0.1.dist-info/top_level.txt
recaptcha_challenger-0.0.1.dist-info/RECORD
